README.md
setup.py
blockpype/__init__.py
blockpype/cli.py
blockpype.egg-info/PKG-INFO
blockpype.egg-info/SOURCES.txt
blockpype.egg-info/dependency_links.txt
blockpype.egg-info/entry_points.txt
blockpype.egg-info/top_level.txt