Metadata-Version: 2.1
Name: blockpype
Version: 1.0.0a1
Summary: Breaks apart input stream into blocks and pipes each block into newly spawned processes
Home-page: https://github.com/kfzteile24/blockpype
Author: kfzteile24 GmbH
License: MIT
Keywords: pipe split buffer block streaming
Platform: UNKNOWN
Classifier: Development Status :: 3 - Alpha
Classifier: Intended Audience :: Developers
Classifier: License :: OSI Approved :: MIT License
Classifier: Programming Language :: Python :: 3.6
Classifier: Programming Language :: Python :: 3.7
Requires-Python: ~=3.6
